edupage_api/__init__.py
edupage_api/classes.py
edupage_api/classrooms.py
edupage_api/cloud.py
edupage_api/compression.py
edupage_api/custom_request.py
edupage_api/dbi.py
edupage_api/exceptions.py
edupage_api/grades.py
edupage_api/login.py
edupage_api/lunches.py
edupage_api/messages.py
edupage_api/module.py
edupage_api/parent.py
edupage_api/people.py
edupage_api/ringing.py
edupage_api/subjects.py
edupage_api/substitution.py
edupage_api/timeline.py
edupage_api/timetables.py
edupage_api/utils.py
edupage_api-0.12.2.dist-info/licenses/LICENSE
edupage_api-0.12.2.dist-info/METADATA
edupage_api-0.12.2.dist-info/WHEEL
edupage_api-0.12.2.dist-info/top_level.txt
edupage_api-0.12.2.dist-info/RECORD
