Metadata-Version: 2.4
Name: edupage_api
Version: 0.12.2
Summary: A Python library for accessing your EduPage account
Home-page: https://github.com/EdupageAPI/edupage-api
Author: ivanhrabcak
Author-email: ivan@hrabcak.eu
Keywords: edupage,edupage api,library
Classifier: Development Status :: 3 - Alpha
Classifier: Intended Audience :: Developers
Classifier: Topic :: Software Development :: Build Tools
Classifier: License :: OSI Approved :: GNU General Public License v3 or later (GPLv3+)
Classifier: Programming Language :: Python :: 3.9
Classifier: Programming Language :: Python :: 3.10
Classifier: Programming Language :: Python :: 3.11
Classifier: Programming Language :: Python :: 3.12
Requires-Python: >=3.9
License-File: LICENSE
Requires-Dist: requests
Dynamic: license-file
